fastapitool/__init__.py
fastapitool/common.py
fastapitool/exceptions.py
fastapitool/model_api.py
fastapitool/rest_api.py
fastapitool/service_io_types.py
fastapitool/simple.py
fastapitool-0.0.2.dist-info/LICENSE
fastapitool-0.0.2.dist-info/METADATA
fastapitool-0.0.2.dist-info/WHEEL
fastapitool-0.0.2.dist-info/top_level.txt
fastapitool-0.0.2.dist-info/RECORD
