Metadata-Version: 2.1
Name: fastapitool
Version: 0.0.2
Summary: Tools for FastAPI
Home-page: https://github.com/stonezhong/fastapitool
Author: Stone Zhong
Author-email: stonezhong@hotmail.com
License: MIT
Classifier: License :: OSI Approved :: MIT License
Classifier: Programming Language :: Python :: 3
License-File: LICENSE
